S2ClusterGen/S2ClusterGen.py
S2ClusterGen/__init__.py
S2ClusterGen-0.0.6.dist-info/LICENSE
S2ClusterGen-0.0.6.dist-info/METADATA
S2ClusterGen-0.0.6.dist-info/WHEEL
S2ClusterGen-0.0.6.dist-info/entry_points.txt
S2ClusterGen-0.0.6.dist-info/top_level.txt
S2ClusterGen-0.0.6.dist-info/RECORD
