Metadata-Version: 2.1
Name: S2ClusterGen
Version: 0.0.6
Summary: S2 - Cluster Generation file
Author-email: Ricardo Santos <rsantos@singlestore.com>
Classifier: Programming Language :: Python :: 3
Classifier: License :: OSI Approved :: MIT License
Classifier: Operating System :: OS Independent
Requires-Python: >=3.9
License-File: LICENSE
